autofactory/__init__.py
autofactory/auto_factory.py
autofactory/pydantic.py
autofactory/sqlalchemy.py
autofactory/utils.py
LibFactory-1.0.2.dist-info/LICENSE
LibFactory-1.0.2.dist-info/METADATA
LibFactory-1.0.2.dist-info/WHEEL
LibFactory-1.0.2.dist-info/top_level.txt
LibFactory-1.0.2.dist-info/RECORD
